MANIFEST.in
README.md
argc.py
setup.py
argc.egg-info/PKG-INFO
argc.egg-info/SOURCES.txt
argc.egg-info/dependency_links.txt
argc.egg-info/top_level.txt
test/test.py