Metadata-Version: 1.0
Name: argc
Version: 2.1.0
Summary: A argument parsing module for python 2 and 3
Home-page: https://github.com/JavadSM/argc
Author: Javad Shafique
Author-email: javadshafique@hotmail.com
License: MIT
Platform: UNKNOWN
